LoIpGen/LoIpGen.py
LoIpGen/__init__.py
LoIpGen-0.0.2.dist-info/METADATA
LoIpGen-0.0.2.dist-info/WHEEL
LoIpGen-0.0.2.dist-info/top_level.txt
LoIpGen-0.0.2.dist-info/RECORD
