Metadata-Version: 2.1
Name: LoIpGen
Version: 0.0.2
Summary: Simple Lorem Ipsum Generator
Home-page: https://github.com/NoemyT/projeto_lorem_ipsum/
Author: NoemyT
Author-email: hatafa123@gmail.com
Requires-Python: >=3.8
